cyclicpeptide/AminoAcids.txt
cyclicpeptide/GraphAlignment.py
cyclicpeptide/IOManager.py
cyclicpeptide/PropertyAnalysis.py
cyclicpeptide/Sequence2Structure.py
cyclicpeptide/SequenceGeneration.py
cyclicpeptide/SequenceTransformer.py
cyclicpeptide/Structure2Sequence.py
cyclicpeptide/StructureTransformer.py
cyclicpeptide/__init__.py
cyclicpeptide/aa_smiles.txt
cyclicpeptide/aas.txt
cyclicpeptide/monomer.tsv
cyclicpeptide/setting.py
cyclicpeptide-1.4.2.dist-info/LICENSE.md
cyclicpeptide-1.4.2.dist-info/METADATA
cyclicpeptide-1.4.2.dist-info/WHEEL
cyclicpeptide-1.4.2.dist-info/top_level.txt
cyclicpeptide-1.4.2.dist-info/RECORD
