Metadata-Version: 2.1
Name: cyclicpeptide
Version: 1.4.2
Summary: A python package for cyclic peptides drug design
Home-page: https://github.com/dfwlab/cyclicpeptide
Author: Willow
Author-email: dfw_bioinfo@126.com
License: MIT
Platform: UNKNOWN
Classifier: Development Status :: 3 - Alpha
Classifier: Intended Audience :: Developers
Classifier: License :: OSI Approved :: MIT License
Classifier: Programming Language :: Python :: 3.8
Requires-Python: >=3.8
License-File: LICENSE.md
Requires-Dist: matplotlib==3.8
Requires-Dist: networkx==3.1
Requires-Dist: numpy==1.24.4
Requires-Dist: pandas==2.0.3
Requires-Dist: rdkit==2023.9.5
Requires-Dist: scipy==1.13.0
Requires-Dist: Ipython==8.0.1
